multiprocesspandas/__init__.py
multiprocesspandas/applyparallel.py
multiprocesspandas-1.1.5.dist-info/LICENSE.txt
multiprocesspandas-1.1.5.dist-info/METADATA
multiprocesspandas-1.1.5.dist-info/WHEEL
multiprocesspandas-1.1.5.dist-info/top_level.txt
multiprocesspandas-1.1.5.dist-info/RECORD
