Metadata-Version: 2.1
Name: multiprocesspandas
Version: 1.1.5
Summary: Extends Pandas to run apply methods for  dataframe, series and groups on multiple cores at same time.
Home-page: https://github.com/akhtarshahnawaz/multiprocesspandas
Download-URL: https://pypi.org/project/multiprocesspandas/
Author: Shahnawaz Akhtar
Author-email: shahnawaz.akhtar@barcelonagse.eu
License: MIT
Keywords: Pandas,Multiprocessing,Pandas Multiprocessing,Parallel,Parallize Pandas
License-File: LICENSE.txt
Requires-Dist: multiprocess (==0.70.11.1)
Requires-Dist: pandas
Requires-Dist: tqdm
Requires-Dist: numpy
